kiosk_common/__init__.py
kiosk_common/agent.py
kiosk_common/emitter.py
kiosk_common/socket.py
kiosk_common-1.0.0.dist-info/LICENSE
kiosk_common-1.0.0.dist-info/METADATA
kiosk_common-1.0.0.dist-info/WHEEL
kiosk_common-1.0.0.dist-info/RECORD
